{"fname":"taxo-jbuf.archaeplastida.streptophyta.magnoliopsida.caryophyllales.caryophyllaceae.saponaria","stub":true,"vault":{"fsPath":".","selfContained":true,"name":"dendron-jbuf"},"schemaStub":false,"type":"note","updated":1676198912438,"created":1676198912438,"id":"2qqo0hxpahkxn10ft3zd23b","desc":"","links":[],"anchors":{},"children":["vhrrlrklqix6ck6ovw66yf2","e67hdvopv2dvgc3vu8h329n","ty3hhqdvqh3udvy3ak7t5vl","9kybv3y0dxbg2vaxjtbmxlp","jmdso8onsy3ex2zehh0t4vj","2o55xd96zcet099507rll88"],"parent":"r2qzqbcfwz9tkujsoeresb8","data":{},"title":"Saponaria"}
