{"fname":"taxo-jbuf.archaeplastida.streptophyta.magnoliopsida.liliales.melanthiaceae","stub":true,"vault":{"fsPath":".","selfContained":true,"name":"dendron-jbuf"},"schemaStub":false,"type":"note","updated":1676198912649,"created":1676198912649,"id":"3zwk8vs12u3gkg96w2i20f7","desc":"","links":[],"anchors":{},"children":["brzafdiuhhvjayzthsskwib","496x9e8d279od16qav2fo52","vqa8pqbrrmtbz5hamdlryey","3wkslgicdwmtybimo4uqm4d","79nzow94gmx9nx2mc60hv0u"],"parent":"q8b6okn87rx8z8zfylqqm84","data":{},"title":"Melanthiaceae"}
