{"fname":"taxo-jbuf.archaeplastida.streptophyta.magnoliopsida.apiales.apiaceae.laserpitium","stub":true,"vault":{"fsPath":".","selfContained":true,"name":"dendron-jbuf"},"schemaStub":false,"type":"note","updated":1676198912135,"created":1676198912135,"id":"63fmww4x8d8halvyr8kahul","desc":"","links":[],"anchors":{},"children":["amlrxmnozhovlyxlir8j54k","hvyuahhmcsb8dreeprozd8c","9jw5bbysqg4vlc1u036vmfr","umuyyu0txz9dxtnleezur1c"],"parent":"ocowfsoxqi2thggeh2t2mvg","data":{},"title":"Laserpitium"}
