{"fname":"taxo-jbuf.archaeplastida.streptophyta.magnoliopsida.asterales","stub":true,"vault":{"fsPath":".","selfContained":true,"name":"dendron-jbuf"},"schemaStub":false,"type":"note","updated":1676198912064,"created":1676198912064,"id":"7ddiuvjwctc5n8bxgr3fe9u","desc":"","links":[],"anchors":{},"children":["4kscn1o4italap36p7lokae","ylx85p1jjm59u8an1jsyvtm","jnbjybprroi1xjjfvpnfv5g","rchti6bxbxuas289jhosjuo","sibffu1ylci2ig5bwdraje4"],"parent":"7n7pwpk669ldo6m7hbpjqa5","data":{},"title":"Asterales"}
