{"fname":"taxo-jbuf.archaeplastida.streptophyta.magnoliopsida.arecales.arecaceae","stub":true,"vault":{"fsPath":".","selfContained":true,"name":"dendron-jbuf"},"schemaStub":false,"type":"note","updated":1676198912147,"created":1676198912147,"id":"b8o176hayxhx9numnjzexd5","desc":"","links":[],"anchors":{},"children":["ml7zga2m40bkn06ai38aksx","0apnoaaydeoi0cguaghzhm4","1jmqiga6jdv31s1ri5p2qkc","bdt5v9wgqffggjo4uuv26xx","rux0xm1dp7qgtjx98ol5zh0","jql58pqb8du357ejj0zvmp8","wxma2srbbtkocjs17f04std","w4w2yide8zhp38uyvwuqppb"],"parent":"yyjbbair55693w5s93hxutf","data":{},"title":"Arecaceae"}
