{"fname":"taxo-jbuf.archaeplastida.streptophyta.magnoliopsida.fabales.fabaceae","stub":true,"vault":{"fsPath":".","selfContained":true,"name":"dendron-jbuf"},"schemaStub":false,"type":"note","updated":1676198912088,"created":1676198912088,"id":"mqmbtiu0m7z5jwbfh4w77dr","desc":"","links":[],"anchors":{},"children":["ge9gbftmo8wdg0v2rdhapho","kzhuixwun3e3k6acpa2xt1d","ahbzn2blh6f457nl7b7i40k","q5nptxbx8cpb0l18ylv23kq","oiqk5lpt37imhiqp5ojp862","h3yr5dfe607mrixeihhqjhq","1dq7cg5lftfa1rasu2zk815","u311mgvy2ecu4mp206lpzri","pza6up0kutgts6cmnhglfgo","lbtpnr59v3j5rvywumjaz66","qts9w9k6j0yihs7pp5j4pur","0ttqbtnsaojiwqbjdde9ipc","qb9mdrdg2cm2jjzsuhtwlrq","xt8mjw596ltlv08x32k6er1","xefdm2ruuslm23uaokxt7c2","runrwmb2vmht8jlm3p5ufdx","0jplswju8jgy6fy2fpybpsb","iranvjq9icaftcuuz7v623p","8wruus05qmkf0juxj9r83fr","7ldxfovz5vml9kdto33lqp3","i0ckuf4t4pem31jeqpz6i0w","oa9lkh1gxkt4x6vxpjypk6s","aj224j4j68vwtoauj5131ws","jwzhkhbaxl8b5uaav51klc2","cw0xtrakuluj6cdegz063at","0vtlxb6xhk6ld5injy7cnzd","8t57o6ejimh0gov4yju041t","peah7a8bronqx8gw6zsbq08","2loiw9dvongcphfdw2m46yc","e3tzpmj1u93y0j41m4ktk4c","a74ppi92tstm24pzsmu60nn","amfy5wb1s4q557zh2xsqg47","abchfl2i2z73p8xn7u0gfe9","n09f845g9m246pjoochdgmy","e0uh45vy11zwkoqvi6gdnz2","qo6eru9aw9liv4deo3rstxn","sc49bycl6oa1g2ocpj1uwh8","uq3ca799athhuqi88jxbckq","7manaetvmhw5f1g6g1tl95t","yxgpitw7051ixv7508pmebo","kfb9kvps5jdske6hlmp1avo","pqsj2kbr185wwab9cf3o7kf","f2o7lijzbnw02xia5ndi3rq","ptlov2sskhvewcmmqmtxzai","keuxzh3ip3vto4o4zle319n","d4uink4h6x555ubgxm1cmgt","bg5zxdabll367tmu4paeg4o","rbfbw5kwprjcsj0zpj353yo","8ieo5ix5j1hp1o07rgy3gxe","ewff3h10otdvi5t04gj4bqq","qq9uvit7gsng9visp62w8b5","p5x0wyrgulp3j2tmsclojpn","59sp5oc2mavggndtdksj9gv","ztfnhgwtjhkgi7f1j7wynxt","1crxy5uwfwjunwfqlr4casf","1muv602v14u1z1jyhaez5v0","fyme3faukej0iib58sj4uss","y7q6t7oelm78rebicez9j2q","slhdylcw2v6wb7jyy644hbf","3k15krgwn7tca0ppdaoi6uc","t1vcgjlr6kdtnrcp08ikl2h","lewzaopr1qxrw2e20y375bs","0ssicr57fgvpf1b6zw5sj4b","pfar3xma6bnjr94onotvs0a","cam8iodwzrvnbgcdub07lc2","w63dvj62rxmxpeuhh9m4y0k","j1ao7u463ngwyglecidlqzh","q543sdhsez89exs5cf3plgs","w1n0rq7bt4thiv0fyq04um8","lugy1drsji2a3we5zd2c8kj","3kntkbfxjn0omzxgee7e122","2ovhkbgn97dvsmrlmmpxab8","mpt3sf8sys7d4cbk3hunkr9","282xgq834v489yxv9z1vamg","4h84z8qgxcu9wwsu28t4rao","3rayvw0b0hengg6vufarxla"],"parent":"sbejp8tl06u22zws1h8gql4","data":{},"title":"Fabaceae"}
