{"fname":"taxo-jbuf.archaeplastida.streptophyta.magnoliopsida.ericales.balsaminaceae.impatiens","stub":true,"vault":{"fsPath":".","selfContained":true,"name":"dendron-jbuf"},"schemaStub":false,"type":"note","updated":1676198912487,"created":1676198912487,"id":"q59117ovzjk3hdxx9f3nd7e","desc":"","links":[],"anchors":{},"children":["0iva0im4ev07c1gz2ex07gw","d9k4kxf4f3fmzc02b2p9bda","i6v7k3c1skl27smvs9s1m4b","78we0o9jb44splqsnftnqnj","9ghe1jpul1ykj9p9lz54j36"],"parent":"h2yz0rttuqrbwgw716clz55","data":{},"title":"Impatiens"}
