{"id":"v4t7qgx83fod5d0j4fwxkff","title":"Lolium Multiflorum","desc":"","updated":1655572208044,"created":1655572208044,"isDir":false,"custom":{"isDir":false},"fname":"taxo-jbuf.archaeplastida.streptophyta.magnoliopsida.poales.poaceae.lolium.lolium-multiflorum","type":"note","vault":{"fsPath":".","selfContained":true,"name":"dendron-jbuf"},"contentHash":"d62f485fef5066e8f07925983ac13158","links":[],"anchors":{"otol-taxonomy":{"type":"header","text":"OTOL Taxonomy","value":"otol-taxonomy","line":11,"column":0,"depth":2},"wikipedia-entry-of-the-taxa":{"type":"header","text":"Wikipedia entry of the taxa","value":"wikipedia-entry-of-the-taxa","line":27,"column":0,"depth":2},"metabolites-found-in-the-taxa":{"type":"header","text":"Metabolites found in the taxa","value":"metabolites-found-in-the-taxa","line":43,"column":0,"depth":2}},"children":[],"parent":"qminolj45gy203b06gvukfp","data":{}}
