{"fname":"taxo-jbuf.archaeplastida.streptophyta.magnoliopsida.malvales.malvaceae.tilia","stub":true,"vault":{"fsPath":".","selfContained":true,"name":"dendron-jbuf"},"schemaStub":false,"type":"note","updated":1676198912678,"created":1676198912678,"id":"vc7vjfqlvqmvsz346zhch6c","desc":"","links":[],"anchors":{},"children":["kvaveasolghaiyds6blnjvh","wu5qy24lc709uo15je0sz0m","sie10s8pta8hepxg4zj6wh6","hydhrkt74frs7tgyqi94e9h","ejfarli0k7ev0asj8hv2o6i"],"parent":"9u6dl2v6h6f5kk6xvbl1g17","data":{},"title":"Tilia"}
