{"id":"ze3etnfownjsz70gs4g7unk","title":"Lavandula Angustifolia","desc":"","updated":1655572208021,"created":1655572208021,"isDir":false,"custom":{"isDir":false},"fname":"taxo-jbuf.archaeplastida.streptophyta.magnoliopsida.lamiales.lamiaceae.lavandula.lavandula-angustifolia","type":"note","vault":{"fsPath":".","selfContained":true,"name":"dendron-jbuf"},"contentHash":"7eab3252f2f716e89aaca51e922b6e1e","links":[],"anchors":{"otol-taxonomy":{"type":"header","text":"OTOL Taxonomy","value":"otol-taxonomy","line":11,"column":0,"depth":2},"wikipedia-entry-of-the-taxa":{"type":"header","text":"Wikipedia entry of the taxa","value":"wikipedia-entry-of-the-taxa","line":27,"column":0,"depth":2},"metabolites-found-in-the-taxa":{"type":"header","text":"Metabolites found in the taxa","value":"metabolites-found-in-the-taxa","line":43,"column":0,"depth":2}},"children":[],"parent":"9zrm9hlarfjftd6l6l7o65j","data":{}}
